clicksearch.py
clicksearch-0.6.0.dist-info/METADATA
clicksearch-0.6.0.dist-info/WHEEL
clicksearch-0.6.0.dist-info/licenses/LICENSE
clicksearch-0.6.0.dist-info/RECORD
