Metadata-Version: 2.3
Name: clicksearch
Version: 0.6.0
Summary: Framework for CLI applications that filter data streams
Project-URL: Homepage, https://github.com/jimorie/clicksearch
Author-email: Petter Nyström <jimorie@gmail.com>
Maintainer-email: Petter Nyström <jimorie@gmail.com>
License: Copyright 2023 Petter Nyström
License-File: LICENSE
Keywords: click
Requires-Python: >=3.9
Requires-Dist: click==8.1.6
Provides-Extra: dev
Requires-Dist: black; extra == 'dev'
Requires-Dist: build; extra == 'dev'
Requires-Dist: bump; extra == 'dev'
Requires-Dist: hatchling; extra == 'dev'
Requires-Dist: mypy; extra == 'dev'
Requires-Dist: ruff; extra == 'dev'
Requires-Dist: twine; extra == 'dev'
